[{"datasetObjectId":"6","dataObject":{"content":"It’s also true that in no time in modern American history has a president’s disposition and rhetoric conflicted more dramatically with the outcomes of his administration. But that has been a net win for the Constitution."},"annotations":[{"workerId":"public.us-east-1.A18FY0P87H4A5O","annotationData":{"content":"{\"category\":{\"label\":\"Biased\"},\"rationale\":\"yes, in modern times president\u0027s disposition and rhetoric outcomes of his administration.\"}"}},{"workerId":"public.us-east-1.A2YO837C0O1E91","annotationData":{"content":"{\"category\":{\"label\":\"Unbiased\"},\"rationale\":\"No one in specific is being singled out.\"}"}}]}]